pygwin/__init__.py
pygwin/_pg.py
pygwin/_win.py
pygwin/color.py
pygwin/console.py
pygwin/font.py
pygwin/gamepad.py
pygwin/image.py
pygwin/keyboard.py
pygwin/mixer.py
pygwin/mouse.py
pygwin/record.py
pygwin/rect.py
pygwin/surface.py
pygwin/tray.py
pygwin/ui.py
pgw-0.4.5.dist-info/LICENSE
pgw-0.4.5.dist-info/METADATA
pgw-0.4.5.dist-info/WHEEL
pgw-0.4.5.dist-info/top_level.txt
pgw-0.4.5.dist-info/RECORD
