Metadata-Version: 2.1
Name: pgw
Version: 0.4.5
Summary: A library for creating Python applications.
Home-page: https://github.com/themixray/pygwin
Author: themixray
Author-email: simindeymo@gmail.com
License: MIT
Project-URL: Bug Tracker, https://github.com/themixray/pygwin/issues
Project-URL: Wiki, https://github.com/themixray/pygwin/wiki
Classifier: Programming Language :: Python :: 3
Classifier: License :: OSI Approved :: MIT License
Classifier: Operating System :: OS Independent
License-File: LICENSE
Requires-Dist: attrdict
Requires-Dist: cython
Requires-Dist: pywin32
Requires-Dist: pygame
Requires-Dist: inputs
Requires-Dist: randstr
Requires-Dist: pydub
Requires-Dist: wxPython
Requires-Dist: pyautogui
Requires-Dist: moviepy
Requires-Dist: pipwin
Requires-Dist: wave
Requires-Dist: opencv-python
Requires-Dist: mutagen
